[
  {
    "instituteName":"Inst-1",
    "code":"code1",
    "registeredDate":"2018-02-15T18:30:00.000Z",
    "logoPath":"../Images/logo.png",
    "address":"KA",
    "city":"Banglore",
    "state":"KA",
    "instituteAdminName":"inst-admin",
    "userName":"inst-user",
    "email":"admin@gmail.com",
    "mobile":1231432
  },
  {
    "instituteName":"Inst-2",
    "code":"code2",
    "registeredDate":"2018-02-09T18:30:00.000Z",
    "logoPath":"../Images/logo.png",
    "address":"AP",
    "city":"Hyd",
    "state":"AP",
    "instituteAdminName":"inst2-admin",
    "userName":"inst2-user",
    "email":"admin@gmail.com",
    "mobile":12341234
  },
  {
    "instituteName":"Inst-3",
    "code":"code3",
    "registeredDate":"2018-02-23T18:30:00.000Z",
    "logoPath":"../Images/logo.png",
    "address":"AP",
    "city":"Hyd",
    "state":"AP",
    "instituteAdminName":"inst3-admin",
    "userName":"inst3-user",
    "email":"admin@gmail.com",
    "mobile":1234123412
  }
  ]